[
    {
      "id": 1,
      "name": "Дизайн ВКонтакте",
      "price": "1499₽",
      "work": "Работа выполняется в течение 2-3 дней по предоплате 50% от стоимости работы.",
      "pack": "В комплект входит: Шапка (Две адаптации), Аватарка, меню (до 5 штук), Товары (До 5 штук).",
      "fix": "Более 5-ти правок оплачивается отдельно - 50₽ (за одну правку)"

    },
    {
      "id": 2,
      "name": "Дизайн ВКонтакте",
      "price": "1499₽",
      "work": "Работа выполняется в течение 2-3 дней по предоплате 50% от стоимости работы.",
      "pack": "В комплект входит: Шапка (Две адаптации), Аватарка, меню (до 5 штук), Товары (До 5 штук).",
      "fix": "Более 5-ти правок оплачивается отдельно - 50₽ (за одну правку)"
    },
    {
      "id": 3,
      "name": "Дизайн ВКонтакте",
      "price": "1499₽",
      "work": "Работа выполняется в течение 2-3 дней по предоплате 50% от стоимости работы.",
      "pack": "В комплект входит: Шапка (Две адаптации), Аватарка, меню (до 5 штук), Товары (До 5 штук).",
      "fix": "Более 5-ти правок оплачивается отдельно - 50₽ (за одну правку)"
    },
    {
      "id": 4,
      "name": "Дизайн ВКонтакте",
      "price": "1499₽",
      "work": "Работа выполняется в течение 2-3 дней по предоплате 50% от стоимости работы.",
      "pack": "В комплект входит: Шапка (Две адаптации), Аватарка, меню (до 5 штук), Товары (До 5 штук).",
      "fix": "Более 5-ти правок оплачивается отдельно - 50₽ (за одну правку)"
    },
    {
      "id": 5,
      "name": "Дизайн ВКонтакте",
      "price": "1499₽",
      "work": "Работа выполняется в течение 2-3 дней по предоплате 50% от стоимости работы.",
      "pack": "В комплект входит: Шапка (Две адаптации), Аватарка, меню (до 5 штук), Товары (До 5 штук).",
      "fix": "Более 5-ти правок оплачивается отдельно - 50₽ (за одну правку)"
    },
    {
      "id": 6,
      "name": "Дизайн ВКонтакте",
      "price": "1499₽",
      "work": "Работа выполняется в течение 2-3 дней по предоплате 50% от стоимости работы.",
      "pack": "В комплект входит: Шапка (Две адаптации), Аватарка, меню (до 5 штук), Товары (До 5 штук).",
      "fix": "Более 5-ти правок оплачивается отдельно - 50₽ (за одну правку)"
    } 
  ]